ppb_vector/__init__.py
ppb_vector-1.0.dist-info/LICENSE.txt
ppb_vector-1.0.dist-info/METADATA
ppb_vector-1.0.dist-info/WHEEL
ppb_vector-1.0.dist-info/top_level.txt
ppb_vector-1.0.dist-info/zip-safe
ppb_vector-1.0.dist-info/RECORD
