Metadata-Version: 2.1
Name: ppb-vector
Version: 1.0
Summary: A basic game development Vector class.
Home-page: https://github.com/ppb/ppb-vector
Author: Piper Thunstrom
Author-email: pathunstrom@gmail.com
License: Artistic-2.0
Platform: UNKNOWN
Classifier: Development Status :: 5 - Production/Stable
Classifier: Intended Audience :: Developers
Classifier: License :: OSI Approved :: Artistic License
Classifier: Topic :: Software Development :: Libraries
Classifier: Topic :: Scientific/Engineering :: Mathematics
Classifier: Programming Language :: Python :: 3
Classifier: Programming Language :: Python :: 3.6
Classifier: Programming Language :: Python :: 3.7
Requires-Python: >= 3.6
Requires-Dist: dataclasses ; python_version < "3.7"
